dropper/.DS_Store
dropper/__init__.py
dropper/dropper.pth
dropper/load_dropper.py
dropper/model.py
dropper/train.py
dropper-0.1.0.dist-info/METADATA
dropper-0.1.0.dist-info/WHEEL
dropper-0.1.0.dist-info/RECORD
