Metadata-Version: 2.3
Name: dropper
Version: 0.1.0
Summary: 
Author: Golos1
Author-email: 68024905+Golos1@users.noreply.github.com
Requires-Python: >=3.12
Classifier: Programming Language :: Python :: 3
Classifier: Programming Language :: Python :: 3.12
Classifier: Programming Language :: Python :: 3.13
Requires-Dist: scikit-learn (>=1.7.1,<2.0.0)
Requires-Dist: torch (>=2.8.0,<3.0.0)
Requires-Dist: torchmetrics (>=1.8.1,<2.0.0)
Requires-Dist: torchvision (>=0.23.0,<0.24.0)
